COPYING
LICENSE.BSD
LICENSE.CCBY
MANIFEST.in
README.MD
setup.py
django_prismriver.egg-info/PKG-INFO
django_prismriver.egg-info/SOURCES.txt
django_prismriver.egg-info/dependency_links.txt
django_prismriver.egg-info/not-zip-safe
django_prismriver.egg-info/top_level.txt
prismriver/__init__.py
prismriver/settings.py
prismriver/views.py
prismriver/dashboard/__init__.py
prismriver/dashboard/admin.py
prismriver/dashboard/models.py
prismriver/dashboard/settings.py
prismriver/dashboard/urls.py
prismriver/dashboard/views.py
prismriver/dashboard/plugins/__init__.py
prismriver/dashboard/plugins/dashplugins.py
prismriver/dashboard/plugins/pluginbase.py
prismriver/static/.DS_Store
prismriver/static/admin/.DS_Store
prismriver/static/admin/css/base.css
prismriver/static/admin/css/changelists.css
prismriver/static/admin/css/dashboard.css
prismriver/static/admin/css/forms.css
prismriver/static/admin/css/ie.css
prismriver/static/admin/css/login.css
prismriver/static/admin/css/override.css
prismriver/static/admin/css/rtl.css
prismriver/static/admin/css/widgets.css
prismriver/static/admin/img/.DS_Store
prismriver/static/admin/img/admin/arrow-down.gif
prismriver/static/admin/img/admin/arrow-up.gif
prismriver/static/admin/img/admin/changelist-bg.gif
prismriver/static/admin/img/admin/changelist-bg_rtl.gif
prismriver/static/admin/img/admin/chooser-bg.gif
prismriver/static/admin/img/admin/chooser_stacked-bg.gif
prismriver/static/admin/img/admin/default-bg-reverse.gif
prismriver/static/admin/img/admin/default-bg.gif
prismriver/static/admin/img/admin/deleted-overlay.gif
prismriver/static/admin/img/admin/enablesidebar.gif
prismriver/static/admin/img/admin/icon-no.gif
prismriver/static/admin/img/admin/icon-unknown.gif
prismriver/static/admin/img/admin/icon-yes.gif
prismriver/static/admin/img/admin/icon_addlink.png
prismriver/static/admin/img/admin/icon_alert.gif
prismriver/static/admin/img/admin/icon_calendar.gif
prismriver/static/admin/img/admin/icon_changelink.png
prismriver/static/admin/img/admin/icon_clock.gif
prismriver/static/admin/img/admin/icon_deletelink copy.png
prismriver/static/admin/img/admin/icon_deletelink.gif
prismriver/static/admin/img/admin/icon_deletelink.png
