Metadata-Version: 1.0
Name: django-prismriver
Version: 0.12
Summary: A light but cool Django admin theme
Home-page: https://bitbucket.org/PolCPP/django-prismriver
Author: Pol Cámara
Author-email: polcamara@soft10.es
License: BSD licence, see LICENCE.txt
Keywords: django admin
Platform: UNKNOWN
